essential/__init__.py
essential/__main__.py
sinehost-0.1.1.dist-info/METADATA
sinehost-0.1.1.dist-info/WHEEL
sinehost-0.1.1.dist-info/entry_points.txt
sinehost-0.1.1.dist-info/top_level.txt
sinehost-0.1.1.dist-info/RECORD
